{
  "name": "Madame Mime",
  "subtitle": "En dragon",
  "strength": 5,
  "willpower": 7,
  "quest_value": 4,
  "rarity": "ENCHANTED",
  "ink_cost": 7,
  "author": "Nicholas Kole",
  "deck_building_id": "8beb7231237cf3bc2a7b1289fd773536113e9112",
  "culture_invariant_id": 424,
  "sort_number": 447,
  "additional_info": [],
  "ink_convertible": true,
  "abilities": [
    "Insaisissable"
  ],
  "subtypes": [
    "Storyborn",
    "Méchant",
    "Mage",
    "Dragon"
  ],
  "flavor_text": "",
  "rules_text": "Insaisissable (Seuls les personnages avec Insaisissable peuvent défier ce personnage.) JE L'AI EU, J'AI GAGNÉ! Lorsque vous jouez ce personnage, bannissez-le ou renvoyez 2 de vos autres personnages en jeu dans votre main.",
  "card_identifier": "208/204 FR 2",
  "image_urls": [
    {
      "height": 2048,
      "url": "https://api.lorcana.ravensburger.com/images/fr/set2/cards/1468x2048/baab34018148392463ef4c49b5a924409cf5f7b0.jpg?checksum=07b133a624d37d1394e63659d1b96eee1dd73b85b6c8ea451dd222ed7ef4a02c"
    },
    {
      "height": 512,
      "url": "https://api.lorcana.ravensburger.com/images/fr/set2/cards/367x512/baab34018148392463ef4c49b5a924409cf5f7b0.jpg?checksum=6803388fbcda70a9727a45eaa5dce15aea5b8efa511feb3819668aee9f2ff3a4"
    }
  ],
  "foil_mask_url": "https://api.lorcana.ravensburger.com/images/fr/set2/masks/1468x2048/baab34018148392463ef4c49b5a924409cf5f7b0.jpg?checksum=173a4c2d140eb8fbc046b034c1d98917a8dee04263ffd4f79a2e593c2b6815fc",
  "foil_type": "Lava",
  "card_sets": [
    2
  ],
  "magic_ink_colors": [
    "AMETHYST"
  ]
}