{
  "name": "Minnie",
  "subtitle": "Plongeuse aux yeux hagards",
  "strength": 6,
  "willpower": 7,
  "quest_value": 2,
  "rarity": "SPECIAL",
  "ink_cost": 7,
  "author": "Gonzalo Kenny",
  "deck_building_id": "4ee51d93e13d4ebe640eb44752aa430fb7dd3afa",
  "culture_invariant_id": 925,
  "sort_number": 945,
  "additional_info": [],
  "ink_convertible": true,
  "abilities": [],
  "subtypes": [
    "Envouté",
    "Héros"
  ],
  "flavor_text": "Le premier – et le meilleur – des Glimmers que j’ai envoutés.%—Ursula",
  "rules_text": "PRÉSENCE DÉROUTANTE Lorsque vous jouez ce personnage, chaque adversaire perd 2 éclats de Lore.",
  "card_identifier": "12/31 FR Q1",
  "image_urls": [
    {
      "height": 2048,
      "url": "https://api.lorcana.ravensburger.com/images/fr/quest1/cards/1468x2048/7b52009b64fd0a2a49e6d8a939753077792b0554.jpg?checksum=6a9a028da096b7ed2a2afab8b4a2ced47ef9446e3d2ab015449df0e87bbea17a"
    },
    {
      "height": 512,
      "url": "https://api.lorcana.ravensburger.com/images/fr/quest1/cards/367x512/7b52009b64fd0a2a49e6d8a939753077792b0554.jpg?checksum=38e3597c0dff88cedae52acd1199910946edba39da2d288339449ad26b11a111"
    }
  ],
  "special_rarity_id": 5,
  "foil_type": "None",
  "card_sets": [
    8
  ],
  "magic_ink_colors": []
}