{
  "name": "Principe Naveen",
  "subtitle": "Suonatore di Ukulele",
  "strength": 3,
  "willpower": 3,
  "quest_value": 2,
  "rarity": "ENCHANTED",
  "ink_cost": 4,
  "author": "Aisha Durmagambetova",
  "deck_building_id": "7019f88f23a40f374d0cc8e7cbb8cb18fd60de3a",
  "culture_invariant_id": 1161,
  "sort_number": 1169,
  "additional_info": [],
  "ink_convertible": false,
  "abilities": [
    "Melodioso"
  ],
  "subtypes": [
    "Classico",
    "Eroe",
    "Principe"
  ],
  "flavor_text": "",
  "rules_text": "Melodioso 6 (Questo personaggio conta come di costo 6 per cantare le canzoni.) È BELLISSIMA, NO? Quando giochi questo personaggio, puoi giocare una canzone con costo 6 o inferiore gratis.",
  "card_identifier": "205/204 IT 5",
  "image_urls": [
    {
      "height": 2048,
      "url": "https://api.lorcana.ravensburger.com/images/it/set5/cards/1468x2048/5f1cd7c3fb68ae7c679f8c33966610670d32ff1e.jpg?checksum=e3aab2e15b181878d1becf2ba56b2b57dbef213d023fbc2df8fe28a49aa7a59a"
    },
    {
      "height": 512,
      "url": "https://api.lorcana.ravensburger.com/images/it/set5/cards/367x512/5f1cd7c3fb68ae7c679f8c33966610670d32ff1e.jpg?checksum=2f6d1a89c54b7b5d1379797e18a951ace6c5ed924f2ff7bdf35d8fb14ccb9a71"
    }
  ],
  "foil_mask_url": "https://api.lorcana.ravensburger.com/images/it/set5/masks/1468x2048/5f1cd7c3fb68ae7c679f8c33966610670d32ff1e.jpg?checksum=80258b02c514476fa9ad4d72d13f728d63276327783a4525b1ca066b82bffc8e",
  "foil_type": "VerticalWave",
  "card_sets": [
    5
  ],
  "magic_ink_colors": [
    "AMBER"
  ]
}