{
  "name": "Winnie the Pooh",
  "subtitle": "Pirata del Miele",
  "strength": 2,
  "willpower": 2,
  "quest_value": 1,
  "rarity": "RARE",
  "ink_cost": 2,
  "author": "Koni",
  "deck_building_id": "f4cb028f3925f704d8e509b9f824df90e1dfdf0e",
  "culture_invariant_id": 1202,
  "sort_number": 1200,
  "additional_info": [],
  "ink_convertible": false,
  "abilities": [
    "Aiutante"
  ],
  "subtypes": [
    "Classico",
    "Eroe",
    "Pirata"
  ],
  "flavor_text": "",
  "rules_text": "Aiutante (Ogni volta che questo personaggio va all’avventura, puoi aggiungere la sua alla di un altro personaggio a tua scelta per questo turno.) SIAMO DEI PIRATI, SAI? Ogni volta che questo personaggio va all'avventura, paga 1 in meno per giocare il tuo prossimo personaggio Pirata per questo turno.",
  "card_identifier": "3/204 IT 6",
  "image_urls": [
    {
      "height": 2048,
      "url": "https://api.lorcana.ravensburger.com/images/it/set6/cards/1468x2048/77de68daecd823babbb58edb1c8e14d7106e83bb.jpg?checksum=79e7984db302dc2cf97f590b5304ea385f6f2a6d8c8193b4d255e42d8b812a71"
    },
    {
      "height": 512,
      "url": "https://api.lorcana.ravensburger.com/images/it/set6/cards/367x512/77de68daecd823babbb58edb1c8e14d7106e83bb.jpg?checksum=617ebd729be89260c59950f6e32570a34f1c731af8faea0eeb549eec6537f454"
    }
  ],
  "foil_mask_url": "https://api.lorcana.ravensburger.com/images/it/set6/masks/1468x2048/77de68daecd823babbb58edb1c8e14d7106e83bb.jpg?checksum=6d1765187971ebd1e98e8c06d98835f2f1855073d319b47652679f79edd4d50f",
  "card_sets": [
    6
  ],
  "magic_ink_colors": [
    "AMBER"
  ]
}