{
  "name": "Spugna",
  "subtitle": "Capitano della Jolly Roger",
  "strength": 3,
  "willpower": 6,
  "quest_value": 2,
  "rarity": "SUPER",
  "ink_cost": 6,
  "author": "Grace Tran",
  "deck_building_id": "f79d27f85394475fadaea68266df26fd8324d52f",
  "culture_invariant_id": 1375,
  "sort_number": 1373,
  "additional_info": [],
  "ink_convertible": false,
  "abilities": [
    "Trasformazione"
  ],
  "subtypes": [
    "Imbevuto",
    "Cattivo",
    "Pirata",
    "Capitano"
  ],
  "flavor_text": "",
  "rules_text": "Trasformazione 4 (Puoi pagare 4 per giocare questa carta sopra a uno dei tuoi personaggi chiamato Spugna.) ISSATE LA BANDIERA Quando giochi questo personaggio, puoi infliggere danno a un personaggio a tua scelta pari al numero dei tuoi altri personaggi Pirata in gioco.",
  "card_identifier": "176/204 IT 6",
  "image_urls": [
    {
      "height": 2048,
      "url": "https://api.lorcana.ravensburger.com/images/it/set6/cards/1468x2048/5c8f5ac0b7ad23c110793ad1fcf4d3c8d41344d5.jpg?checksum=f179ce941b6117649e4130273b461ca3c0e243b31ef098aa78c6f804590d69a1"
    },
    {
      "height": 512,
      "url": "https://api.lorcana.ravensburger.com/images/it/set6/cards/367x512/5c8f5ac0b7ad23c110793ad1fcf4d3c8d41344d5.jpg?checksum=91b17f2a9d0fc39791462f54f3949d5fbeb95a3970f6e97d8ea380b04718726b"
    }
  ],
  "foil_mask_url": "https://api.lorcana.ravensburger.com/images/it/set6/masks/1468x2048/5c8f5ac0b7ad23c110793ad1fcf4d3c8d41344d5.jpg?checksum=419cebb257f3cdbc903fc41c61ce10093a2389937e704f749f32e7647f612c85",
  "card_sets": [
    6
  ],
  "magic_ink_colors": [
    "STEEL"
  ]
}