{
  "name": "Alma Madrigal",
  "subtitle": "Family Matriarch",
  "strength": 1,
  "willpower": 3,
  "quest_value": 2,
  "rarity": "RARE",
  "ink_cost": 3,
  "author": "Maxine Vee",
  "deck_building_id": "18a98fa235abcf4d0b586d93830e89dc0ca67460",
  "culture_invariant_id": 693,
  "sort_number": 702,
  "additional_info": [],
  "ink_convertible": false,
  "abilities": [],
  "subtypes": [
    "Storyborn",
    "Mentor",
    "Madrigal"
  ],
  "flavor_text": "Let's be clear, Abuela runs this show. —Mirabel",
  "rules_text": "TO THE TABLE When you play this character, you may search your deck for a Madrigal character card and reveal that card to all players. Shuffle your deck and put that card on top of it.",
  "card_identifier": "2/204 EN 4",
  "image_urls": [
    {
      "height": 2048,
      "url": "https://api.lorcana.ravensburger.com/images/en/set4/cards/1468x2048/da4b9237bacccdf19c0760cab7aec4a8359010b0.jpg?checksum=ca1a44e76be8f311ed7ddb62038e6e7690db2672b7dd37a7f56f6eb4e747436e"
    },
    {
      "height": 512,
      "url": "https://api.lorcana.ravensburger.com/images/en/set4/cards/367x512/da4b9237bacccdf19c0760cab7aec4a8359010b0.jpg?checksum=e7b8b310982dc8a264274cd2b1c88bef08933a58a15db08c98fdf4aa05f2f3b9"
    }
  ],
  "foil_mask_url": "https://api.lorcana.ravensburger.com/images/en/set4/masks/1468x2048/da4b9237bacccdf19c0760cab7aec4a8359010b0.jpg?checksum=3a0a5145a0090527d45b6c456ff9d086d3c264bd01bd88563d033dfbb521d7b5",
  "card_sets": [
    4
  ],
  "magic_ink_colors": [
    "AMBER"
  ]
}