{
  "name": "Wasabi",
  "subtitle": "Methodical Engineer",
  "strength": 3,
  "willpower": 3,
  "quest_value": 1,
  "rarity": "SPECIAL",
  "ink_cost": 4,
  "author": "Taraneh",
  "deck_building_id": "4c44b7fca1f2f6a3616e9dc982897df5179befa0",
  "culture_invariant_id": 1428,
  "sort_number": 1425,
  "additional_info": [],
  "ink_convertible": true,
  "abilities": [],
  "subtypes": [
    "Storyborn",
    "Hero",
    "Inventor"
  ],
  "flavor_text": "",
  "rules_text": "BLADES OF FURY When you play this character, you may banish chosen item. Its player gains 1 lore. QUICK REFLEXES During your turn, this character gains Evasive. (They can challenge characters with Evasive.)",
  "card_identifier": "13/P2 EN 6",
  "image_urls": [
    {
      "height": 2048,
      "url": "https://api.lorcana.ravensburger.com/images/en/promo2/cards/1468x2048/bd307a3ec329e10a2cff8fb87480823da114f8f4.jpg?checksum=958eb0fc531fc374eb652690c852dcd53b1bd98f937af9a7a5a5478e96e78758"
    },
    {
      "height": 512,
      "url": "https://api.lorcana.ravensburger.com/images/en/promo2/cards/367x512/bd307a3ec329e10a2cff8fb87480823da114f8f4.jpg?checksum=1e862d3fd423f030f1a01d51095094b563c75c91a80f724d9948d1436f44b944"
    }
  ],
  "foil_mask_url": "https://api.lorcana.ravensburger.com/images/en/promo2/masks/1468x2048/bd307a3ec329e10a2cff8fb87480823da114f8f4.jpg?checksum=126c2958b0ffde622b38d33c90aae90e320166386d2294646199e8aeecc5c9ed",
  "special_rarity_id": 1,
  "foil_type": "Silver",
  "card_sets": [
    6
  ],
  "magic_ink_colors": [
    "SAPPHIRE"
  ]
}