{
  "name": "Tamatoa",
  "subtitle": "Grabby Crab",
  "strength": 3,
  "willpower": 6,
  "quest_value": 2,
  "rarity": "SPECIAL",
  "ink_cost": 4,
  "author": "Luigi Aimé",
  "deck_building_id": "cf75ca665114b363f6d8903c8c48ca3bea1b8353",
  "culture_invariant_id": 928,
  "sort_number": 948,
  "additional_info": [],
  "ink_convertible": true,
  "abilities": [],
  "subtypes": [
    "Entangled",
    "Villain"
  ],
  "flavor_text": "It’s called a distraction, angelfish. Look it up. —Ursula",
  "rules_text": "PICK ONE! When you play this character, the opposing players together choose an item or location of theirs and banish it.",
  "card_identifier": "15/31 EN Q1",
  "image_urls": [
    {
      "height": 2048,
      "url": "https://api.lorcana.ravensburger.com/images/en/quest1/cards/1468x2048/f1abd670358e036c31296e66b3b66c382ac00812.jpg?checksum=b34ce8e130688773ec69cdb42630c364b8d89c19bd0b8959b2ebebcb38005ec2"
    },
    {
      "height": 512,
      "url": "https://api.lorcana.ravensburger.com/images/en/quest1/cards/367x512/f1abd670358e036c31296e66b3b66c382ac00812.jpg?checksum=5472e800e8fab85ca1d7bb7447fe859c87b55edf5154b87423a1904c70149608"
    }
  ],
  "special_rarity_id": 5,
  "foil_type": "None",
  "card_sets": [
    8
  ],
  "magic_ink_colors": []
}